Metadata-Version: 2.1
Name: pym3u8
Version: 0.1.5
Summary: Simple Python 3 lib for downloading online HLS streams and videos
Home-page: https://github.com/ndrwpvlv/pym3u8
Author: Andrei S. Pavlov
Author-email: ndrw.pvlv@gmail.com
License: MIT
Download-URL: https://github.com/ndrwpvlv/pym3u8/archive/0.1.5.tar.gz
Keywords: M3U8,HLS,STREAM,VIDEO
Platform: UNKNOWN
Classifier: Programming Language :: Python :: 3.5
Classifier: Programming Language :: Python :: 3.6
Classifier: Programming Language :: Python :: 3.7
Classifier: Operating System :: OS Independent
Classifier: License :: OSI Approved :: MIT License
